[{"Timestamp":1467461042449035155,"Event":"YGCwFwAAAAEAAAAAAAAAAAAAAAA=","IsWrite":true,"Completed":true,"Error":null},{"Timestamp":1467461042449387274,"Event":"AAAAAQ==","IsWrite":false,"Completed":false,"Error":null},{"Timestamp":1467461042449405737,"Event":"ACSyAdATR29sYW5nTmVvNGpCb2x0LzEuMKGGc2NoZW1lhG5vbmUAAA==","IsWrite":true,"Completed":true,"Error":null},{"Timestamp":1467461042449583816,"Event":"AAOxcKAAAA==","IsWrite":false,"Completed":true,"Error":null},{"Timestamp":1467461042449636503,"Event":"AA2yEIlSRVRVUk4gMTugAAA=","IsWrite":true,"Completed":true,"Error":null},{"Timestamp":1467461042449670678,"Event":"AAKwPwAA","IsWrite":true,"Completed":true,"Error":null},{"Timestamp":1467461042450038953,"Event":"AA2xcKGGZmllbGRzkYExAAA=","IsWrite":false,"Completed":true,"Error":null},{"Timestamp":1467461042450076550,"Event":"AASxcZEBAAA=","IsWrite":false,"Completed":true,"Error":null},{"Timestamp":1467461042450090711,"Event":"AAqxcKGEdHlwZYFyAAA=","IsWrite":false,"Completed":true,"Error":null}]
